clothion/__init__.py
pytere/__init__.py
clothion-0.1.0.dist-info/LICENSE
clothion-0.1.0.dist-info/METADATA
clothion-0.1.0.dist-info/WHEEL
clothion-0.1.0.dist-info/top_level.txt
clothion-0.1.0.dist-info/RECORD
